sns_core/__init__.py
sns_core/exceptions.py
sns_core/objects.py
sns_core/parser.py
sns_core/records.py
sns_core/requests.py
sns_core/server.py
sns_core/sessions.py
sns_core/utils.py
tests/__init__.py
tests/test_exceptions.py
tests/test_objects.py
tests/test_parser.py
tests/test_records.py
tests/test_requests.py
tests/test_server.py
sns_core-0.0.16.dist-info/LICENSE
sns_core-0.0.16.dist-info/METADATA
sns_core-0.0.16.dist-info/WHEEL
sns_core-0.0.16.dist-info/top_level.txt
sns_core-0.0.16.dist-info/RECORD
