Metadata-Version: 2.1
Name: sns-core
Version: 0.0.16
Summary: SNS-core provides all the core functions to communicate using the SNS protocol.
Home-page: https://pypi.org/project/sns-core/
Author: Soter Company
Author-email: soter.business@gmail.com
License: UNKNOWN
Platform: UNKNOWN
Classifier: Programming Language :: Python :: 3
Classifier: License :: OSI Approved :: MIT License
Classifier: Operating System :: OS Independent
Requires-Python: >=3.6
